{
  "_comment": "NON-AUTHORITATIVE EXAMPLE — StageVerify dev-host reference only. Copy and rename for your project.",
  "targetName": "stageverify",
  "orchestrationProfile": "composer-default",
  "memory": {
    "router": "PROJECT_STATUS/MEMORY.md",
    "hot": "PROJECT_STATUS/CURRENT_STATE.md",
    "warm": "PROJECT_STATUS/MODEL_DOSSIER.md",
    "phase": "docs/project_state.md",
    "roadmap": "docs/roadmap.md",
    "next": "NEXT.md"
  },
  "ship": {
    "deploy": "npm run deploy",
    "rulesDeploy": "firebase deploy --only firestore:rules --project YOUR-PROJECT-ID"
  },
  "verify": {
    "pickup": "npm run verify:pickup",
    "devPort": 5173
  },
  "trials": ".cursor/trials.json"
}
